setup.cfg
setup.py
mold/__init__.py
mold/codegen.py
mold/context.py
mold/environment.py
mold/parser.py
mold/template.py
mold/tokenizer.py
pymold.egg-info/PKG-INFO
pymold.egg-info/SOURCES.txt
pymold.egg-info/dependency_links.txt
pymold.egg-info/top_level.txt