Metadata-Version: 1.1
Name: pymold
Version: 0.1.3
Summary: A simple, fast template engine for Python.
Home-page: https://github.com/Bogdanp/mold
Author: Bogdan Popa
Author-email: popa.bogdanp@gmail.com
License: UNKNOWN
Keywords: web
Platform: UNKNOWN
Classifier: Development Status :: 3 - Alpha
Classifier: License :: OSI Approved :: MIT License
